processors/__init__.py
processors/annotators.py
processors/api.py
processors/ds.py
processors/odin.py
processors/paths.py
processors/sentiment.py
processors/serialization.py
processors/utils.py
processors/visualization.py
processors/assets/displacy-processors.css
processors/assets/displacy-processors.html
processors/assets/displacy-processors.js
processors/assets/mentions.css
processors/assets/parse.css
processors/tests/example-rules.yml
processors/tests/obama.txt
processors/tests/serialized_biodoc.json
processors/tests/serialized_doc.json
processors/tests/serialized_mention.json
processors/tests/serialized_obama.json
processors/tests/serialized_sentence.json
py_processors-3.2.2.dist-info/DESCRIPTION.rst
py_processors-3.2.2.dist-info/METADATA
py_processors-3.2.2.dist-info/RECORD
py_processors-3.2.2.dist-info/WHEEL
py_processors-3.2.2.dist-info/metadata.json
py_processors-3.2.2.dist-info/top_level.txt
