Metadata-Version: 2.0
Name: py-processors
Version: 3.2.2
Summary: A wrapper for interacting with the CLU Lab's processors library.
Home-page: http://github.com/myedibleenso/py-processors
Author: myedibleenso
Author-email: gushahnpowell@gmail.com
License: Apache 2.0
Download-URL: https://github.com/myedibleenso/py-processors/archive/v3.2.2.zip
Keywords: nlp,processors,jvm
Platform: UNKNOWN
Classifier: Intended Audience :: Science/Research
Classifier: Natural Language :: English
Classifier: Topic :: Scientific/Engineering :: Artificial Intelligence
Classifier: Programming Language :: Python :: 2.7
Classifier: Programming Language :: Python :: 3
Requires-Dist: six
Requires-Dist: requests (>=2.4.2)
Requires-Dist: networkx (==1.11)
Requires-Dist: termcolor (>=1.1.0)
Provides-Extra: jupyter
Requires-Dist: jupyter (>=1.0.0); extra == 'jupyter'
Requires-Dist: ipython (>=6.2.1); extra == 'jupyter'
Requires-Dist: traitlets (>=4.3.2); extra == 'jupyter'
Provides-Extra: test
Requires-Dist: green (>=2.5.0); extra == 'test'
Requires-Dist: coverage; extra == 'test'
